screenshotmax/__init__.py
screenshotmax/client.py
screenshotmax/enums.py
screenshotmax/options.py
screenshotmax/sdk.py
screenshotmax/services/__init__.py
screenshotmax/services/device.py
screenshotmax/services/pdf.py
screenshotmax/services/scrape.py
screenshotmax/services/screencast.py
screenshotmax/services/screenshot.py
screenshotmax/services/task.py
screenshotmax/services/usage.py
screenshotmax-1.0.1.dist-info/licenses/LICENSE
screenshotmax-1.0.1.dist-info/METADATA
screenshotmax-1.0.1.dist-info/WHEEL
screenshotmax-1.0.1.dist-info/top_level.txt
screenshotmax-1.0.1.dist-info/RECORD
