Metadata-Version: 2.4
Name: screenshotmax
Version: 1.0.1
Summary: Official Python SDK for ScreenshotMAX API
Author-email: Bertrand Lebonnois <support@screenshotmax.com>
License-Expression: MIT
Project-URL: Homepage, https://screenshotmax.com
Project-URL: Repository, https://github.com/screenshotmax/python-sdk
Project-URL: Documentation, https://docs.screenshotmax.com
Classifier: Development Status :: 5 - Production/Stable
Classifier: Intended Audience :: Developers
Classifier: Topic :: Internet :: WWW/HTTP
Classifier: Programming Language :: Python :: 3
Classifier: Programming Language :: Python :: 3.9
Classifier: Programming Language :: Python :: 3.10
Classifier: Programming Language :: Python :: 3.11
Requires-Python: >=3.9
License-File: LICENSE
Requires-Dist: requests>=2.25.1
Dynamic: license-file
